MANIFEST.in
README.rst
RELEASE
VERSION
setup.cfg
setup.py
setup_requirements.txt
devtools/__init__.py
devtools/code_generator.py
devtools/crawler.py
devtools/source_engine.py
devtools/template_engine.py
f5/__init__.py
f5/sdk_exception.py
f5-sdk-dist/__init__.py
f5-sdk-dist/add_pkg_name.py
f5-sdk-dist/build_pkgs.py
f5-sdk-dist/scripts/__init__.py
f5-sdk-dist/scripts/build_exceptions.py
f5-sdk-dist/scripts/build_expectations.py
f5-sdk-dist/scripts/configure.py
f5-sdk-dist/scripts/construct_setups.py
f5-sdk-dist/scripts/get-version-release.py
f5-sdk-dist/scripts/install_test.py
f5-sdk-dist/scripts/terminal.py
f5/bigip/__init__.py
f5/bigip/contexts.py
f5/bigip/mixins.py
f5/bigip/resource.py
f5/bigip/cm/__init__.py
f5/bigip/cm/system.py
f5/bigip/cm/autodeploy/__init__.py
f5/bigip/cm/autodeploy/software_images.py
f5/bigip/shared/__init__.py
f5/bigip/shared/authn.py
f5/bigip/shared/authz.py
f5/bigip/shared/file_transfer.py
f5/bigip/shared/iapp.py
f5/bigip/tm/__init__.py
f5/bigip/tm/analytics/__init__.py
f5/bigip/tm/analytics/dos_vis_common.py
f5/bigip/tm/asm/__init__.py
f5/bigip/tm/asm/attack_types.py
f5/bigip/tm/asm/file_transfer.py
f5/bigip/tm/asm/policy_templates.py
f5/bigip/tm/asm/signature_sets.py
f5/bigip/tm/asm/signature_statuses.py
f5/bigip/tm/asm/signature_systems.py
f5/bigip/tm/asm/signature_update.py
f5/bigip/tm/asm/signatures.py
f5/bigip/tm/asm/tasks.py
f5/bigip/tm/asm/policies/__init__.py
f5/bigip/tm/asm/policies/audit_logs.py
f5/bigip/tm/asm/policies/blocking_settings.py
f5/bigip/tm/asm/policies/brute_force.py
f5/bigip/tm/asm/policies/character_sets.py
f5/bigip/tm/asm/policies/cookies.py
f5/bigip/tm/asm/policies/csrf_protection.py
f5/bigip/tm/asm/policies/data_guard.py
f5/bigip/tm/asm/policies/extractions.py
f5/bigip/tm/asm/policies/filetypes.py
f5/bigip/tm/asm/policies/general.py
f5/bigip/tm/asm/policies/geolocation_enforcement.py
f5/bigip/tm/asm/policies/gwt_profiles.py
f5/bigip/tm/asm/policies/headers.py
f5/bigip/tm/asm/policies/history_revisions.py
f5_sdk.egg-info/PKG-INFO
f5_sdk.egg-info/SOURCES.txt
f5_sdk.egg-info/dependency_links.txt
f5_sdk.egg-info/entry_points.txt
f5_sdk.egg-info/requires.txt
f5_sdk.egg-info/top_level.txt
